{
  "__class__": "Network", 
  "capacity": {
    "__class__": "Multidict", 
    "items": [
      [
        [
          "N8", 
          "N9"
        ], 
        [
          3, 
          5
        ]
      ], 
      [
        [
          "N1", 
          "N2"
        ], 
        [
          3, 
          5
        ]
      ], 
      [
        [
          "N2", 
          "N3"
        ], 
        [
          3, 
          5
        ]
      ], 
      [
        [
          "N5", 
          "N6"
        ], 
        [
          3, 
          5
        ]
      ], 
      [
        [
          "N7", 
          "N8"
        ], 
        [
          3, 
          5
        ]
      ], 
      [
        [
          "N0", 
          "N1"
        ], 
        [
          3, 
          5
        ]
      ], 
      [
        [
          "N4", 
          "N5"
        ], 
        [
          3, 
          5
        ]
      ], 
      [
        [
          "N6", 
          "N7"
        ], 
        [
          3, 
          5
        ]
      ], 
      [
        [
          "N3", 
          "N4"
        ], 
        [
          3, 
          5
        ]
      ]
    ]
  }, 
  "links": [
    [
      "N8", 
      "N9"
    ], 
    [
      "N1", 
      "N2"
    ], 
    [
      "N2", 
      "N3"
    ], 
    [
      "N5", 
      "N6"
    ], 
    [
      "N7", 
      "N8"
    ], 
    [
      "N0", 
      "N1"
    ], 
    [
      "N4", 
      "N5"
    ], 
    [
      "N6", 
      "N7"
    ], 
    [
      "N3", 
      "N4"
    ]
  ], 
  "nodes": {
    "N0": [
      0.0, 
      0.0
    ], 
    "N1": [
      0.08964491911022976, 
      0.0
    ], 
    "N2": [
      0.21724224333966013, 
      0.0
    ], 
    "N3": [
      0.3145673602006563, 
      0.0
    ], 
    "N4": [
      0.46440797775393156, 
      0.0
    ], 
    "N5": [
      0.5502743834947246, 
      0.0
    ], 
    "N6": [
      0.6961064915473744, 
      0.0
    ], 
    "N7": [
      0.7807769577377012, 
      0.0
    ], 
    "N8": [
      0.9335744314709151, 
      0.0
    ], 
    "N9": [
      1.0, 
      0.0
    ]
  }, 
  "route_dirs": {
    "0": [], 
    "N0-N9": [
      1, 
      1, 
      1, 
      1, 
      1, 
      1, 
      1, 
      1, 
      1
    ], 
    "N9-N0": [
      0, 
      0, 
      0, 
      0, 
      0, 
      0, 
      0, 
      0, 
      0
    ]
  }, 
  "route_links": {
    "0": [], 
    "N0-N9": [
      [
        "N0", 
        "N1"
      ], 
      [
        "N1", 
        "N2"
      ], 
      [
        "N2", 
        "N3"
      ], 
      [
        "N3", 
        "N4"
      ], 
      [
        "N4", 
        "N5"
      ], 
      [
        "N5", 
        "N6"
      ], 
      [
        "N6", 
        "N7"
      ], 
      [
        "N7", 
        "N8"
      ], 
      [
        "N8", 
        "N9"
      ]
    ], 
    "N9-N0": [
      [
        "N8", 
        "N9"
      ], 
      [
        "N7", 
        "N8"
      ], 
      [
        "N6", 
        "N7"
      ], 
      [
        "N5", 
        "N6"
      ], 
      [
        "N4", 
        "N5"
      ], 
      [
        "N3", 
        "N4"
      ], 
      [
        "N2", 
        "N3"
      ], 
      [
        "N1", 
        "N2"
      ], 
      [
        "N0", 
        "N1"
      ]
    ]
  }, 
  "route_nodes": {
    "0": [], 
    "N0-N9": [
      "N0", 
      "N1", 
      "N2", 
      "N3", 
      "N4", 
      "N5", 
      "N6", 
      "N7", 
      "N8", 
      "N9"
    ], 
    "N9-N0": [
      "N9", 
      "N8", 
      "N7", 
      "N6", 
      "N5", 
      "N4", 
      "N3", 
      "N2", 
      "N1", 
      "N0"
    ]
  }, 
  "routes": {
    "0": [], 
    "N0-N9": [
      "N0", 
      "N1", 
      "N2", 
      "N3", 
      "N4", 
      "N5", 
      "N6", 
      "N7", 
      "N8", 
      "N9"
    ]
  }
}